Metadata-Version: 2.1
Name: filelistener
Version: 1.0.3
Summary: A tool to find duplicate content within a folder and its subdirectories and gives you an option to delete it.
Author: Rishabh Pandey
Author-email: brikjr@outlook.com
